chosco/VERSION
chosco/__init__.py
chosco/annotation/__init__.py
chosco/annotation/application/__init__.py
chosco/annotation/application/annotator_builder.py
chosco/annotation/domain/__init__.py
chosco/annotation/domain/annotation.py
chosco/annotation/domain/annotation_repository.py
chosco/annotation/domain/annotation_session.py
chosco/annotation/domain/annotation_task_provider.py
chosco/annotation/domain/annotation_task_status.py
chosco/annotation/domain/aggregate_roots/__init__.py
chosco/annotation/domain/aggregate_roots/media_item.py
chosco/annotation/infrastructure/__init__.py
chosco/annotation/infrastructure/inmemory_annotation_repository.py
chosco/annotation/infrastructure/json_annotation_task_provider.py
chosco/annotation/infrastructure/json_folder_annotation_repository.py
chosco/media/__init__.py
chosco/media/repository/__init__.py
chosco/media/repository/domain/__init__.py
chosco/media/repository/domain/media_repository.py
chosco/media/repository/infrastructure/__init__.py
chosco/media/repository/infrastructure/gcp_bucket_media_repository.py
chosco/media/repository/infrastructure/gcp_bucket_multimedia_repository.py
chosco/media/repository/infrastructure/hardcoded_web_media_repository.py
chosco/media/retriever/__init__.py
chosco/media/retriever/domain/__init__.py
chosco/media/retriever/domain/media_retriever.py
chosco/view/__init__.py
chosco/view/interactor/__init__.py
chosco/view/interactor/annotation_view_interactor.py
chosco/view/interactor/domain/__init__.py
chosco/view/interactor/domain/metadata_formatter.py
chosco/view/interactor/domain/view_interactor.py
chosco-0.3.6.dist-info/LICENSE
chosco-0.3.6.dist-info/METADATA
chosco-0.3.6.dist-info/WHEEL
chosco-0.3.6.dist-info/top_level.txt
chosco-0.3.6.dist-info/RECORD
