Metadata-Version: 2.1
Name: chosco
Version: 0.3.6
Summary: Package on top of ipywidgets to label media resources on Notebook pages.
Home-page: https://github.com/alice-biometrics/chosco
Author: ALiCE Biometrics
Author-email: support@alicebiometrics.com
License: MIT
Keywords: notebook,ipywidgets,labeler
Platform: UNKNOWN
Classifier: License :: OSI Approved :: MIT License
Classifier: Programming Language :: Python
Classifier: Programming Language :: Python :: 3
License-File: LICENSE
Requires-Dist: google-cloud-storage (==1.44.0)
Requires-Dist: numpy (>=1.19.5)
Requires-Dist: ipywidgets (==7.6.5)
Requires-Dist: loguru
